[{"date": "20200102", "reseller-id": 1001, "productName": "5.5x8.5 All the love from Valencia", "qty": 4, "totalAmount": 13.2, "salesChannel": "mobile app", "customer": {"firstname": "Karoline", "lastname": "Webb", "email": "Karoline.Webb@example.com"}, "dateCreated": "20200102", "seriesCity": "Valencia", "Created Date": "2020-01-02", "transactionId": 3}, {"date": "20200102", "reseller-id": 1001, "productName": "5.5x8.5 Greetings from Sevilla", "qty": 6, "totalAmount": 22.799999999999997, "salesChannel": "mobile app", "customer": {"firstname": "Pearline", "lastname": "Swartz", "email": "Pearline.Swartz@example.com"}, "dateCreated": "20200102", "seriesCity": "Sevilla", "Created Date": "2020-01-02", "transactionId": 4}]